dhashpy/__init__.py
dhashpy/__version__.py
dhashpy/dHash.py
dhashpy-1.0.2.dist-info/LICENSE
dhashpy-1.0.2.dist-info/METADATA
dhashpy-1.0.2.dist-info/WHEEL
dhashpy-1.0.2.dist-info/top_level.txt
dhashpy-1.0.2.dist-info/RECORD
